usbcloner/__init__.py
usbcloner/__main__.py
usbcloner/config_handler.py
usbcloner/duplication.py
usbcloner/renaming.py
usbcloner/usb_handler.py
usbcloner/verification.py
usbcloner-0.1.0.dist-info/LICENSE
usbcloner-0.1.0.dist-info/METADATA
usbcloner-0.1.0.dist-info/WHEEL
usbcloner-0.1.0.dist-info/entry_points.txt
usbcloner-0.1.0.dist-info/top_level.txt
usbcloner-0.1.0.dist-info/RECORD
