Metadata-Version: 2.1
Name: usbcloner
Version: 0.1.0
Summary: Clones the contents of USB drives and verifies successful duplication
Author-email: usbcloner <usbcloner@proton.me>
License: GNU GENERAL PUBLIC LICENSE
Keywords: usb,drive,clone,mirror,duplicate,verify,copy,replicate,replication,distribute,distribution
Classifier: Development Status :: 3 - Alpha
Classifier: Environment :: Console
Classifier: License :: OSI Approved :: GNU General Public License v3 (GPLv3)
Classifier: Natural Language :: English
Classifier: Operating System :: POSIX :: Linux
Classifier: Programming Language :: Python :: 3 :: Only
Classifier: Topic :: Communications :: File Sharing
Classifier: Topic :: System :: Archiving :: Mirroring
Classifier: Topic :: System :: Hardware :: Universal Serial Bus (USB)
Classifier: Topic :: System :: Software Distribution
Requires-Python: >=3.8
License-File: LICENSE
Requires-Dist: mmh3
Requires-Dist: pyudev
